wallctl/__init__.py
wallctl/__main__.py
wallctl/base.py
wallctl/cli.py
wallctl/parser.py
wallctl-0.2.0.dist-info/LICENSE
wallctl-0.2.0.dist-info/METADATA
wallctl-0.2.0.dist-info/WHEEL
wallctl-0.2.0.dist-info/entry_points.txt
wallctl-0.2.0.dist-info/top_level.txt
wallctl-0.2.0.dist-info/RECORD
